pax25/__init__.py
pax25/applications/__init__.py
pax25/applications/application.py
pax25/applications/autocomplete.py
pax25/applications/help.py
pax25/applications/parsers.py
pax25/applications/router.py
pax25/applications/types.py
pax25/applications/utils.py
pax25/ax25/__init__.py
pax25/ax25/address.py
pax25/ax25/constants.py
pax25/ax25/control.py
pax25/ax25/exceptions.py
pax25/ax25/frame.py
pax25/ax25/matchers.py
pax25/ax25/protocols.py
pax25/ax25/utils.py
pax25/conftest.py
pax25/contrib/__init__.py
pax25/contrib/bulletin_board/__init__.py
pax25/contrib/bulletin_board/bulletin_board.py
pax25/contrib/bulletin_board/types.py
pax25/contrib/command/__init__.py
pax25/contrib/command/command.py
pax25/contrib/command/commands/__init__.py
pax25/contrib/command/commands/admin.py
pax25/contrib/command/commands/utilities.py
pax25/contrib/command/shim.py
pax25/contrib/command/types.py
pax25/contrib/echo.py
pax25/contrib/exec.py
pax25/exceptions.py
pax25/frame_router.py
pax25/interfaces/__init__.py
pax25/interfaces/dummy.py
pax25/interfaces/file.py
pax25/interfaces/kiss/__init__.py
pax25/interfaces/kiss/constants.py
pax25/interfaces/kiss/protocol.py
pax25/interfaces/loopback.py
pax25/interfaces/serial.py
pax25/interfaces/tcp.py
pax25/interfaces/tcp_kiss.py
pax25/interfaces/types.py
pax25/protocols.py
pax25/services/__init__.py
pax25/services/beacon.py
pax25/services/connection/__init__.py
pax25/services/connection/connection.py
pax25/services/connection/service.py
pax25/services/connection/variables.py
pax25/services/digipeater.py
pax25/services/monitor.py
pax25/station.py
pax25/timer.py
pax25/types.py
pax25/utils.py
pax25-0.8.0.dist-info/WHEEL
pax25-0.8.0.dist-info/METADATA
pax25-0.8.0.dist-info/RECORD
