Metadata-Version: 2.3
Name: pax25
Version: 0.8.0
Summary: A complete AX.25 stack and application library.
Author: Fox Piacenti, Lion Templin
Author-email: Fox Piacenti <fox@artconomy.com>, Lion Templin <lion@lion.fm>
Classifier: Development Status :: 2 - Pre-Alpha
Classifier: Programming Language :: Python :: 3
Classifier: License :: OSI Approved :: GNU Affero General Public License v3 or later (AGPLv3+)
Classifier: Operating System :: OS Independent
Requires-Dist: pyserial>=3.5
Requires-Python: >=3.14
Project-URL: Homepage, https://docs.pax25.com/
Project-URL: Bug Tracker, https://gitlab.com/FoxyFoxie/pax25/-/issues
